{"cameraMode":{"drawMode":0,"name":"Shaded","section":"Shading Mode"},"sceneLighting":true,"audioPlay":false,"sceneViewState":{"m_AlwaysRefresh":false,"showFog":true,"showSkybox":true,"showFlares":true,"showImageEffects":true,"showParticleSystems":true,"showVisualEffectGraphs":true,"m_FxEnabled":true},"in2DMode":false,"pivot":{"x":752.7041625976563,"y":176.3695831298828,"z":-247.66355895996095},"rotation":{"x":-0.0842704325914383,"y":0.4113210141658783,"z":-0.03623885661363602,"w":-0.9071906208992004},"size":1.2159504890441895,"orthographic":false}